{"id": "", "cityID": "241", "url": "http://www.etwarm.com.tw/rent-178343", "title": "新北三重臨捷運站單人套房出租", "address": "新北市三重區介壽路39巷", "pattern": "NA", "floor": 3, "stories": 5, "label": "套", "rent": 6000, "lat": 25.0704884, "lng": 121.5011932, "sex": "A", "space": 7.0, "smoke": "N", "pet": "N", "cook": "N", "updateDate": "2017-08-16", "landlord": "屋主林先生,0988370162", "description": "\n特色推薦\n(新北市三重區介壽路39巷..歡迎先去看街道環境.有意者再來電) (.租金6000元 含水費、寬頻網路、第四台)  \n\r\n  (鄰近光榮國中.捷運三重國小站) \n\r\n巷子小，有對外窗及曬衣空間\n\r\n獨立衛浴與門戶.水泥隔間 \r\n套房約6坪大.為狹長空間. .( 扣除家具家電後.只有能再容納約一個單人床大小的走道.若不嫌棄者歡迎)\r\n交通便利近蘆洲線三重國小捷運站.台北橋等\n\r\n生活機能優 近三和夜市商圈.\r\n**絕對謝絕養寵物的房客**\n\r\n聯絡電話:0988370162林先生\r\n 立即可入住\n\r\n提供設備：\t\r\n床.衣櫃.電視.冷氣.冰箱.熱水器.洗衣機.有線電視.網路\r\n生活機能：近便利商店；傳統市場；學校；夜市;捷運站;\r\n可遷入\r\n搶拼出租！！ \r\n★     本處套房皆為房東自租，絕非仲介或二房東，看屋不論是否承租，絕對不收取\n\r\n任何服務或仲介費用，歡迎來電預約看屋！！\r\n水費、寬頻網路、第四台.每月至少省1０００元，不景氣中房東咬牙苦撐\n\n\n", "temp": "Y"}